brute.py
brute-0.0.3.dist-info/DESCRIPTION.rst
brute-0.0.3.dist-info/METADATA
brute-0.0.3.dist-info/metadata.json
brute-0.0.3.dist-info/RECORD
brute-0.0.3.dist-info/top_level.txt
brute-0.0.3.dist-info/WHEEL
